liveprofiler_sampler/__init__.py
liveprofiler_sampler-0.9.3.dist-info/DESCRIPTION.rst
liveprofiler_sampler-0.9.3.dist-info/METADATA
liveprofiler_sampler-0.9.3.dist-info/RECORD
liveprofiler_sampler-0.9.3.dist-info/WHEEL
liveprofiler_sampler-0.9.3.dist-info/metadata.json
liveprofiler_sampler-0.9.3.dist-info/top_level.txt
