Metadata-Version: 2.0
Name: liveprofiler-sampler
Version: 0.9.3
Summary: Module for sampling profiling output from the main process
Home-page: https://github.com/fieldaware/liveprofiler_sampler
Author: Piotr Szymanski
Author-email: piotr.szymanski@fieldaware.com
License: MIT
Platform: UNKNOWN
